hawt/__init__.py
hawt/identity_center.py
hawt/main.py
hawt/sso_auth.py
hawt-0.1.2.dist-info/WHEEL
hawt-0.1.2.dist-info/entry_points.txt
hawt-0.1.2.dist-info/METADATA
hawt-0.1.2.dist-info/RECORD
