Metadata-Version: 2.1
Name: hawt
Version: 0.1.2
Summary: Highspot Amazon Web Services Tools; convenicance functions that automate certain security tasks.
Author: Anthony Lozano
Author-email: tony.lozano@highspot.com
Requires-Python: >=3.11,<4.0
Classifier: Programming Language :: Python :: 3
Classifier: Programming Language :: Python :: 3.11
Requires-Dist: appdirs (>=1.4.4,<2.0.0)
Requires-Dist: boto3 (>=1.26.105,<2.0.0)
Requires-Dist: boto3-stubs-lite[essential,identitystore,sso,sso-oidc] (>=1.26.105,<2.0.0)
Requires-Dist: mypy (>=1.1.1,<2.0.0)
Requires-Dist: typer[all] (>=0.7.0,<0.8.0)
